{
  "aggs": {
    "avg": {
      "avg": {
        "field": "intervaltime"
      }
    },
    "max": {
      "max": {
        "field": "intervaltime"
      }
    },
    "min": {
      "min": {
        "field": "intervaltime"
      }
    }
  },
  "size": 0,
  "query": {
    "bool": {
      "filter": [
        {
          "term": {
            "packageNm": #{packageNm}
          }
        },
        {
          "term": {
            "serverType": #{serverType}
          }
        }
        #[isAppVer]
        ,{
          "term": {
            "appVer": #{appVer}
          }
        }
        #[/isAppVer]
        ,{
          "term": {
            "osType": #{osType}
          }
        },
        {
          "range": {
            "logTm": {
              "from": #{fromYearTimestamp},
              "to": #{toYearTimestamp},
              "include_lower": true,
              "include_upper": true,
              "time_zone": "Z"
            }
          }
        }
      ],
      "must_not": [
        {
          "term": {
            "intervaltime": "0"
          }
        }
      ]
    }
  }
}